{"categories":["Security"],"desc":"A Practical Guide to TPM 2.0: Using the Trusted Platform Module in the New Age of Security","details":{"authors":"Will Arthur, David Challener","format":"pdf","isbn-10":"1430265833","isbn-13":"978-1430265832","pages":"392 pages","publication date":"January 24, 2015","publisher":"Apress","size":"5.09Mb"},"img":"http://23.95.221.108/covers/64/6479e1993766961a60719f0318ee6e0c.jpg","link":"https://rapidhosting.info/files/dtj","title":"A Practical Guide to TPM 2.0: Using the Trusted Platform Module in the New Age of Security"}