{"categories":["Engineering","Uncategorized"],"desc":"Learn the latest techniques in programming sophisticated simulation systems","details":{"authors":"Granino A. Korn","format":"pdf","isbn-10":"0470081880","isbn-13":"978-0470081884","pages":"221 pages","publication date":"February 2, 2007","publisher":"Wiley-Interscience","size":"3.34Mb"},"img":"http://23.95.221.108/covers/94/94008d95ed09249b8da891c62303a72c.jpg","link":"https://rapidhosting.info/files/9uf","title":"Advanced Dynamic-system Simulation: Model-replication Techniques and Monte Carlo Simulation"}