{"categories":["Programming","Uncategorized"],"desc":"The papers in this volume cover a broad spectrum of topics that represent the truly diverse nature of the field of composite materials. This collection presents research and findings relevant to the latest advances in composites materials, specifically their use in aerospace, maritime, and even land applications. The editors have made every effort to bring together authors who put forth recent advances in their research while concurrently both elaborating on and thereby enhancing our prevailing understanding of the salient aspects related to the science, engineering, and far-reaching technological applications of composite materials.","details":{"authors":"Tomoko Sano, T. S. Srivatsan, Michael W. Peretti","format":"pdf","isbn-10":"111888891X","isbn-13":"978-1118888919","pages":"304 pages","publication date":"March 10, 2014","publisher":"Wiley-TMS","size":"6.63Mb"},"img":"http://23.95.221.108/covers/b6/b661ced47760d40a4a94b91401568fbd.jpg","link":"https://rapidhosting.info/files/aa1","title":"Advanced Composites for Aerospace, Marine, and Land Applications"}