{"categories":["Computing","Engineering","Robotics"],"desc":"\n","details":{"authors":"Jessie Chen","format":"pdf","isbn-10":"3319603833","isbn-13":"978-3319603834","pages":"358 pages","publication date":"July 19, 2017","publisher":"Springer","size":"36.11Mb"},"img":"http://23.95.221.108/covers/41/4171cb39537b512387e190d0c0804433.jpg","link":"https://rapidhosting.info/files/clw","title":"Advances in Human Factors in Robots and Unmanned Systems: Proceedings of the AHFE 2017 International Conference on Human Factors in Robots and … in Intelligent Systems and Computing)"}