{"categories":["Designing","Hardware"],"desc":"\n","details":{"authors":"Ricardo Martins, Nuno Lourenço, Nuno Horta","format":"pdf","isbn-10":"331934059X","isbn-13":"978-3319340593","pages":"207 pages","publication date":"July 21, 2016","publisher":"Springer","size":"10.00Mb"},"img":"http://23.95.221.108/covers/0d/0def6b91d9ae7b9041b68b6394e08b33.jpg","link":"https://rapidhosting.info/files/au6","title":"Analog Integrated Circuit Design Automation: Placement, Routing and Parasitic Extraction Techniques"}