{"categories":["Uncategorized"],"desc":" Completely revised and updated for Logic Pro 9 and Logic Express 9, this Apple-certified guide shows you how to record, produce, and polish music files with Apple’s professional audio software. Veteran music producer David Nahmani’s step-by-step, instructions teach you everything from basic music creation to advanced production techniques using Logic’s software synthesizers, samplers, and digital signal processors. Using the book’s DVD files and either Logic Pro 9 or Logic Express 9, you’ll begin making music in the first lesson. Whether you’re looking to use your computer as a digital recording studio, create musical compositions, or transfer that song in your head into music you can share, this comprehensive book/DVD combo will show you how.","details":{"authors":"David Nahmani","format":"pdf","isbn-10":"0321636805","isbn-13":"978-0321636805","pages":"504 pages","publication date":"November 16, 2009","publisher":"Peachpit Press","size":"23.00Mb"},"img":"http://23.95.221.108/covers/38/389a6bc510aef55c90cb7fde91067a83.jpg","link":"https://rapidhosting.info/files/g6t","title":"Apple Pro Training Series: Logic Pro 9 and Logic Express 9"}