{"categories":["Engineering","Programming"],"desc":" ","details":{"authors":"Warren B. Powell","format":"pdf","isbn-10":"047060445X","isbn-13":"978-0470604458","pages":"606 pages","publication date":"September 27, 2011","publisher":"Wiley","size":"4.00Mb"},"img":"http://23.95.221.108/covers/36/36d8677b7a42038e3d7e5ff670dded73.jpg","link":"https://rapidhosting.info/files/dwt","title":"Approximate Dynamic Programming: Solving the Curses of Dimensionality, 2nd Edition (Wiley Series in Probability and Statistics)"}