{"categories":["Data Management","Data Mining","Programming","Web Development"],"desc":"\n","details":{"authors":"Peter Meißner","format":"pdf","isbn-10":"111883481X","isbn-13":"978-1118834817","pages":"474 pages","publication date":"January 20, 2015","publisher":"Wiley","size":"4.00Mb"},"img":"http://23.95.221.108/covers/02/0277b1635e200081f20fb47b646ca388.jpg","link":"https://rapidhosting.info/files/9wh","title":"Automated Data Collection with R: A Practical Guide to Web Scraping and Text Mining"}