{"categories":["Data Mining","Manual"],"desc":"\n","details":{"authors":"Alan T. Norman","format":"azw3","isbn-10":"1979688362","isbn-13":"978-1979688369","pages":"162 pages","publication date":"November 13, 2017","publisher":"CreateSpace Independent Publishing Platform","size":"1.66Mb"},"img":"http://23.95.221.108/covers/d3/d3552f683667a55a9f7425b1b7d2ccd1.jpg","link":"https://rapidhosting.info/files/9u1","title":"Cryptocurrency Investing Bible: The Ultimate Guide About Blockchain, Mining, Trading, ICO, Ethereum Platform, Exchanges, Top Cryptocurrencies for Investing and Perfect Strategies to Make Money"}