{"categories":["Data Management","Databases","Engineering","Software"],"desc":" Useful business analysis requires you to effectively transform data into actionable information. This book helps you use SQL and Excel to extract business information from relational databases and use that data to define business dimensions, store transactions about customers, produce results, and more. Each chapter explains when and why to perform a particular type of business analysis in order to obtain useful results, how to design and perform the analysis using SQL and Excel, and what the results should look like.","details":{"authors":"Gordon S. Linoff","format":"pdf","isbn-10":"0470099518","isbn-13":"978-0470099513","pages":"645 pages","publication date":"October 1, 2007","publisher":"Wiley","size":"18.80Mb"},"img":"http://23.95.221.108/covers/51/51178e2dd001ba767519af41f5e9ca69.jpg","link":"https://rapidhosting.info/files/9li","title":"Data Analysis Using SQL and Excel"}