{"categories":["Data Management","Data Mining","Engineering","Management"],"desc":"\n","details":{"authors":"Jian Pei","format":"pdf","isbn-10":"9380931913","isbn-13":"978-9380931913","pages":"744 pages","publication date":"July 6, 2011","publisher":"Morgan Kaufmann","size":"12.00Mb"},"img":"http://23.95.221.108/covers/81/819138b9694c5e4ad690566ac92063c6.jpg","link":"https://rapidhosting.info/files/7rz","title":"Data Mining: Concepts and Techniques, Third Edition (The Morgan Kaufmann Series in Data Management Systems)"}