{"categories":["Data Management","Engineering","Programming"],"desc":"\n","details":{"authors":"Francesco Palumbo, Angela Montanari, Maurizio Vichi","format":"pdf","isbn-10":"331955722X","isbn-13":"978-3319557229","pages":"342 pages","publication date":"August 2, 2017","publisher":"Springer","size":"7.00Mb"},"img":"http://23.95.221.108/covers/92/92016a3955bc7c5e8e399117f3900c4e.jpg","link":"https://rapidhosting.info/files/8xj","title":"Data Science: Innovative Developments in Data Analysis and Clustering (Studies in Classification, Data Analysis, and Knowledge Organization)"}