{"categories":["Mobile Development","Networking","Telecommunications"],"desc":"\n","details":{"authors":"Mohesen Guizani, Hsiao-Hwa Chen, Chonggang Wang","format":"pdf","isbn-10":"1482220946","isbn-13":"978-1482220940","pages":"462 pages","publication date":"September 22, 2015","publisher":"CRC Press","size":"7.00Mb"},"img":"http://23.95.221.108/covers/4c/4c39ebcac6d93a621cd635e8999c0d58.jpg","link":"https://rapidhosting.info/files/9jf","title":"The Future of Wireless Networks: Architectures, Protocols, and Services (Wireless Networks and Mobile Communications)"}