{"categories":["Uncategorized"],"desc":" With an emphasis on real-world math applications, the Sixth Edition of INTRODUCTORY TECHNICAL MATHEMATICS provides readers with current and practical technical math applications for today’s sophisticated trade and technical work environments. Straightforward and easy to understand, this hands-on book helps readers build a solid understanding of math concepts through step-by-step examples and problems drawn from various occupations. Updated to include the most current information in the field, the sixth edition includes expanded coverage of topics such as estimation usage, spreadsheets, and energy-efficient electrical applications.","details":{"authors":"John Peterson, Robert D. Smith","format":"pdf","isbn-10":"1111542015","isbn-13":"978-1111542016","pages":"896 pages","publication date":"September 19, 2012","publisher":"Delmar Cengage Learning","size":"69.07Mb"},"img":"http://23.95.221.108/covers/cd/cd8e479dc5e5de5cd48875a5a00518e1.jpg","link":"https://rapidhosting.info/files/dmh","title":"Introductory Technical Mathematics"}