{"categories":["Programming"],"desc":" INTRODUCTION TO PYTHON PROGRAMMING AND DEVELOPING GUI APPLICATIONS WITH PYQT 1E teaches Python programming step-by-step through practical examples that readers can see in action right away. It begins with a solid introduction of Python from scratch, covering loops, control structures, sequences, functions, classes, and exception handling. Thereafter, the book explores file handling and GUI application development in PyQT, the powerful cross-platform GUI layout and forms builder that allows programmers to rapidly design and build widgets and dialogs. This is a great book for newbie programmers interested in learning Python","details":{"authors":"B. M. Harwani","format":"pdf","isbn-10":"1435460979","isbn-13":"978-1435460973","pages":"416 pages","publication date":"December 1, 2011","publisher":"Cengage Learning PTR","size":"19.00Mb"},"img":"http://23.95.221.108/covers/2d/2de8c971354e546e7a2b5054f9a644d9.jpg","link":"https://rapidhosting.info/files/7us","title":"Introduction to Python Programming and Developing GUI Applications with PyQT"}