{"categories":["Manual"],"desc":" Bridging the gap between the palm-sized iPod touch and a full-sized computer, Apple’s iPad offers enough screen area and horsepower to perform the day-to-day tasks most people want to do. Packed with practical knowledge, this book will walk readers through how to manage their most common projects, from the simple (setting up a calendar event) to the complex (planning a vacation) and everything in between. Readers will learn to use the iPad tools and applications by using them to create practical real-world projects and to master everyday tasks.","details":{"authors":"Dennis Cohen","format":"pdf","isbn-10":"032171475X","isbn-13":"978-0321714756","pages":"240 pages","publication date":"September 19, 2010","publisher":"Peachpit Press","size":"37.00Mb"},"img":"http://23.95.221.108/covers/5d/5d554ea5ac942e97952bcf72822f35e5.jpg","link":"https://rapidhosting.info/files/fsa","title":"The iPad Project Book"}