{"categories":["Designing","Manual","Programming","Scripting","Web Development"],"desc":"\n","details":{"authors":"Addy Osmani","format":"pdf","isbn-10":"1449331815","isbn-13":"978-1449331818","pages":"254 pages","publication date":"August 30, 2012","publisher":"O'Reilly Media","size":"2.32Mb"},"img":"http://23.95.221.108/covers/08/08f6168945c836449f3e40e6c170ad67.jpg","link":"https://rapidhosting.info/files/com","title":"Learning JavaScript Design Patterns: A JavaScript and jQuery Developer’s Guide"}