{"categories":["Cloud Computing","Management","Manual","Networking"],"desc":"\n","details":{"authors":null,"format":"epub","isbn-10":"1788993179","isbn-13":"978-1788993173","pages":"385 pages","publication date":"June 11, 2018","publisher":"Packt Publishing - ebooks Account","size":"3.85Mb"},"img":"http://23.95.221.108/covers/3f/3f70ce97b2fa74f794bf019ac36dbca5.jpg","link":"https://rapidhosting.info/files/ha4","title":"Mastering pfSense 2.4: Master the art of managing, securing, and monitoring your on-premises and Cloud network using the powerful pfSense 2.4.3"}