{"categories":["Data Management","Machine Learning","Management","Manual","Software"],"desc":"\n","details":{"authors":"Brett Powell","format":"epub","isbn-10":"1788290143","isbn-13":"978-1788290142","pages":"802 pages","publication date":"September 27, 2017","publisher":"Packt Publishing - ebooks Account","size":"18.51Mb"},"img":"http://23.95.221.108/covers/6d/6d4d473b8667daef2932485ce3c84413.jpg","link":"https://rapidhosting.info/files/cu7","title":"Microsoft Power BI Cookbook: Creating Business Intelligence Solutions of Analytical Data Models, Reports, and Dashboards"}