{"categories":["Telecommunications"],"desc":" The high level of technical detail included in standards specifications can make it difficult to find the correlation between the standard specifications and the theoretical results. This book aims to cover both of these elements to give accessible information and support to readers. It explains the current and future trends on communication theory and shows how these developments are implemented in contemporary wireless communication standards.","details":{"authors":"Evgenii Krouk, Sergei Semenov","format":"pdf","isbn-10":"0470745053","isbn-13":"978-0470745052","pages":"680 pages","publication date":"February 21, 2011","publisher":"Wiley","size":"8.00Mb"},"img":"http://23.95.221.108/covers/98/98a5738e8bf314af3238a5a1f90ac594.jpg","link":"https://rapidhosting.info/files/eld","title":"Modulation and Coding Techniques in Wireless Communications"}