{"categories":["Engineering"],"desc":" An insightful guide to understanding and visualizing multivariate statistics using SAS®, STATA®, and SPSS®  ","details":{"authors":"Bruce L. Brown, Suzanne B. Hendrix, Dawson W. Hedges, Timothy B. Smith","format":"pdf","isbn-10":"0470537566","isbn-13":"978-0470537565","pages":"496 pages","publication date":"December 27, 2011","publisher":"Wiley","size":"7.00Mb"},"img":"http://23.95.221.108/covers/85/851078caf1562eed82e1f09f4a2b1191.jpg","link":"https://rapidhosting.info/files/cee","title":"Multivariate Analysis for the Biobehavioral and Social Sciences: A Graphical Approach"}