{"categories":["Databases","Manual","Web Development"],"desc":" With special focus on the next major release of MySQL, this resource provides a solid framework for anyone new to MySQL or transitioning from another database platform, as well as experience MySQL administrators. The high-profile author duo provides essential coverage of the fundamentals of MySQL database management—including MySQL’s unique approach to basic database features and functions—as well as coverage of SQL queries, data and index types, stores procedure and functions, triggers and views, and transactions. They also present comprehensive coverage of such topics as MySQL server tuning, managing storage engines, caching, backup and recovery, managing users, index tuning, database and performance monitoring, security, and more.","details":{"authors":"Sheeri K. Cabral, Keith Murphy","format":"pdf","isbn-10":"0470416912","isbn-13":"978-0470416914","pages":"888 pages","publication date":"May 11, 2009","publisher":"Wiley","size":"17.00Mb"},"img":"http://23.95.221.108/covers/4e/4ed02578127d383248b11eda5c607886.jpg","link":"https://rapidhosting.info/files/b4o","title":"MySQL Administrator’s Bible"}