{"categories":["Digital Design/Media","Manual"],"desc":" This book is an example-driven introduction to OGRE 3D. Each example shows some new features and you learn step-by-step to create complex scenes with different effects using OGRE 3D. After several examples discussing one topic there is a do-it-yourself part where you will be challenged to solve problems on your own. If you have ever wanted to develop 3D applications with OGRE 3D, this example-driven book will enable you to do so. Understanding of C++ is needed to follow the examples in the book.","details":{"authors":"Felix Kerger","format":"pdf","isbn-10":"1849512485","isbn-13":"978-1849512480","pages":"300 pages","publication date":"November 24, 2010","publisher":"Packt Publishing","size":"5.00Mb"},"img":"http://23.95.221.108/covers/2f/2f7821c6cafe5789f13b6460abe969aa.jpg","link":"https://rapidhosting.info/files/7sy","title":"OGRE 3D 1.7 Beginner’s Guide (Learn by Doing: Less Theory, More Results)"}