{"categories":["Management","Web Development"],"desc":" This book not only describes the need for Web Services security but also explains with detailed examples how to define security policies and enforce those policies using Oracle Web Services Manager. This book emphasizes how to use Oracle WSM to address various security use cases with detailed step-by-step examples to learn Oracle Web Service Manager. This is the book for those who want to learn how to Secure web services and Use Oracle WSM to configure web services security. It is mainly for Developers and Architects who want to learn how to use Oracle WSM to address the security challenges of web services and those who want to learn how to use Oracle WSM to address their security needs. If you have a basic knowledge of Web Services then this book will help you understand the need for security and how to use Oracle WSM to address the security challenges.","details":{"authors":"Sitaraman Lakshminarayanan","format":"pdf","isbn-10":"1847193838","isbn-13":"978-1847193834","pages":"236 pages","publication date":"July 10, 2008","publisher":"Packt Publishing","size":"10.37Mb"},"img":"http://23.95.221.108/covers/93/93dce8b642bf63b8e387678c1211fb02.jpg","link":"https://rapidhosting.info/files/b85","title":"Oracle Web Services Manager: Securing your Web Services"}