{"categories":["Computational Biology","Programming","Security"],"desc":"\n","details":{"authors":null,"format":"pdf","isbn-10":"3319255266","isbn-13":"978-3319255262","pages":"375 pages","publication date":"January 11, 2017","publisher":"Springer","size":"15.53Mb"},"img":"http://23.95.221.108/covers/01/010da665e4fb1d0c89cdebb7c20fec25.jpg","link":"https://rapidhosting.info/files/hf7","title":"Programming Languages with Applications to Biology and Security: Essays Dedicated to Pierpaolo Degano on the Occasion of His 65th Birthday"}