{"categories":["Data Management","Programming","Scripting","Web Development"],"desc":" This book is a fast-paced guide full of step-by-step instructions that teach you how to visualize social data using HTML5 and JavaScript. This book is for developers who are excited about data and who want to share that excitement with others. Developers who are interested in the data which can be extracted from social networks will also find this book hugely beneficial. Readers should have a working knowledge of both JavaScript and HTML.","details":{"authors":"Simon Timms","format":"pdf","isbn-10":"1782166548","isbn-13":"978-1782166542","pages":"104 pages","publication date":"September 25, 2013","publisher":"Packt Publishing","size":"1.00Mb"},"img":"http://23.95.221.108/covers/76/76f9772095ab97b2867d7c1a18d37b02.jpg","link":"https://rapidhosting.info/files/bi5","title":"Social Data Visualization with HTML5 and JavaScript"}