{"categories":["Databases","Manual"],"desc":" Build a core level of competency in SQL so you can recognize the parts of queries and write simple SQL statements. SQL knowledge is essential for anyone involved in programming, data science, and data management. This book covers features of SQL that are standardized and common across most database vendors. You will gain a base of knowledge that will prepare you to go deeper into the specifics of any database product you might encounter. ","details":{"authors":null,"format":"pdf","isbn-10":"1484235754","isbn-13":"978-1484235751","pages":"194 pages","publication date":"August 10, 2018","publisher":"Apress","size":"2.29Mb"},"img":"http://23.95.221.108/covers/e8/e8995a12d044817781a9d8fe278291b6.jpg","link":"https://rapidhosting.info/files/hfb","title":"SQL Primer: An Accelerated Introduction to SQL Basics"}