{"categories":["Engineering","Machine Learning","Networking"],"desc":"\n","details":{"authors":"Wuneng Zhou, Jun Yang, Liuwei Zhou, Dongbing Tong","format":"epub","isbn-10":"3662478323","isbn-13":"978-3662478325","pages":"357 pages","publication date":"August 14, 2015","publisher":"Springer","size":"7.20Mb"},"img":"http://23.95.221.108/covers/26/26f40975ae2824d44125180309fcd06a.jpg","link":"https://rapidhosting.info/files/h24","title":"Stability and Synchronization Control of Stochastic Neural Networks (Studies in Systems, Decision and Control)"}