{"categories":["Networking","Programming","Telecommunications"],"desc":"\n","details":{"authors":"Song Guo, Guiyi Wei, Yang Xiang, Xiaodong Lin, Pascal Lorenz","format":"pdf","isbn-10":"3319495798","isbn-13":"978-3319495798","pages":"179 pages","publication date":"December 29, 2016","publisher":"Springer","size":"23.00Mb"},"img":"http://23.95.221.108/covers/37/376109ca2f69bd35a1309c1b5a83ca0e.jpg","link":"https://rapidhosting.info/files/elj","title":"Testbeds and Research Infrastructures for the Development of Networks and Communities"}