{"categories":["Designing","Management","Programming","Web Development"],"desc":" One of the world leaders in Enterprise Content Management, the EMC Documentum family of applications helps you manage all types of content across multiple departments within a single repository. With the Web Content Management suite of applications, you can efficiently manage content and underlying processes for your Web properties, and ensures that they are responsive to business needs. To fully realize the power of this system can seem daunting, but this book will help you achieve that. With easy to follow examples, this book will take you the simplest and most straightforward route to success. Along the way, you will learn insights that only a seasoned professional would know. Packed with practical examples, you will get hands-on with the powerful features of Documentum to grow your skills and confidence. You will see tips and tricks to handle complexities of the system, and avoid the common errors that waste your time. From installing and getting started with Documentum, you will see how to design and develop Documentum applications, before rounding off with deployment. This book is targeted at IT professionals who are Documentum beginners or intermediates. The depth of coverage means that experienced Documentum developers will also benefit from the book, and learn some new tricks. Although no knowledge of Documentum is presumed, exposure to Java/J2EE, XML, and related web technologies will help to get the most from this book.","details":{"authors":"Gaurav Kathuria","format":"pdf","isbn-10":"1904811094","isbn-13":"978-1904811091","pages":"484 pages","publication date":"June 25, 2006","publisher":"Packt Publishing","size":"9.59Mb"},"img":"http://23.95.221.108/covers/b1/b18244e6621ecc39cef03ff6c0e55e7c.jpg","link":"https://rapidhosting.info/files/a5e","title":"Web Content Management with Documentum: Setup, Design, Develop, and Deploy Documentum Applications"}