{"categories":["Tips and Tricks","Web Development"],"desc":" Remember when an optimized website was one that merely didn’t take all day to appear? Times have changed. Today, website optimization can spell the difference between enterprise success and failure, and it takes a lot more know-how to achieve success. ","details":{"authors":"Andrew B. King","format":"pdf","isbn-10":"0596515081","isbn-13":"978-0596515089","pages":"398 pages","publication date":"July 18, 2008","publisher":"O'Reilly Media","size":"7.88Mb"},"img":"http://23.95.221.108/covers/76/76f78b29aa4e7d3a52329c2ad595e998.jpg","link":"https://rapidhosting.info/files/dgc","title":"Website Optimization: Speed, Search Engine & Conversion Rate Secrets"}